{"_id":{"$oid":"5be5893150750f4e586fd62b"},"active":true,"firstName":"Derrick","lastName":"Little","photoUrl":"https://s3.amazonaws.com/uifaces/faces/twitter/mattlat/128.jpg","company":"DuBuque Group","position":"Foreperson, supervisor, lead person","password":"Maz/fUycZtrN3BNdMpmYHHUmQZgJiY/JmBOhSHFQEo4=","contacts":[{"$oid":"5be5893250750f4e586fd630"},{"$oid":"5be5893250750f4e586fd633"},{"$oid":"5be5893250750f4e586fd634"},{"$oid":"5be5893250750f4e586fd639"},{"$oid":"5be5893250750f4e586fd632"},{"$oid":"5be5893250750f4e586fd63d"}],"username":"derrick39","email":"derricklittle09@hotmail.com","tel":"390-711-0741 x73394","id":"5be5893150750f4e586fd62b","createdAt":{"$date":"2018-11-09T13:18:41.873Z"},"updatedAt":{"$date":"2018-11-09T13:29:35.762Z"},"salt":"TPo126bubFMUD6sL7y5GUQ==","__v":1}
{"_id":{"$oid":"5be5893250750f4e586fd62c"},"active":true,"firstName":"Elbert","lastName":"Moen","photoUrl":"https://s3.amazonaws.com/uifaces/faces/twitter/fronx/128.jpg","company":"Kris LLC","position":"Operations manager","password":"9Xu2F7wqXVm1whXC0WHv80ybdy/zOjQB62QFWT3Dgtw=","contacts":[{"$oid":"5be5893250750f4e586fd632"},{"$oid":"5be5893250750f4e586fd633"},{"$oid":"5be5893250750f4e586fd63c"},{"$oid":"5be5893250750f4e586fd634"},{"$oid":"5be5893250750f4e586fd63d"},{"$oid":"5be5893250750f4e586fd638"}],"username":"elbert.moen","email":"elbert50@gmail.com","tel":"1-365-242-5681 x5164","id":"5be5893250750f4e586fd62c","createdAt":{"$date":"2018-11-09T13:18:42.225Z"},"updatedAt":{"$date":"2018-11-09T13:29:35.776Z"},"salt":"al78ybUdf6wkb6FldyiN4Q==","__v":1}
{"_id":{"$oid":"5be5893250750f4e586fd62d"},"active":true,"firstName":"Rene","lastName":"Boyer","photoUrl":"https://s3.amazonaws.com/uifaces/faces/twitter/ashernatali/128.jpg","company":"Kilback-Sipes LLC","position":"Quality control, safety, environmental manager.","password":"0BdiOI46Wc70G+sJkiJk7B4CRC0gwqPOmFfnhgX+8s0=","contacts":[{"$oid":"5be5893250750f4e586fd635"},{"$oid":"5be5893250750f4e586fd634"}],"username":"rene.boyer0231","email":"rene.boyer22@yahoo.com","tel":"1-976-759-4460","id":"5be5893250750f4e586fd62d","createdAt":{"$date":"2018-11-09T13:18:42.235Z"},"updatedAt":{"$date":"2018-11-09T16:07:13.293Z"},"salt":"MOMDLV/UMGu0ZpLrmS4fnQ==","__v":1,"tokenExpire":1542168433}
{"_id":{"$oid":"5be5893250750f4e586fd62e"},"active":true,"firstName":"Elena","lastName":"Prohaska","photoUrl":"https://s3.amazonaws.com/uifaces/faces/twitter/evandrix/128.jpg","company":"Von Corp.","position":"Professional staff","password":"d+O6P1M6VFr6ypjs68jx8jJ1HJq168TMstVGJZ6diYk=","contacts":[{"$oid":"5be5893250750f4e586fd62c"},{"$oid":"5be5893250750f4e586fd635"},{"$oid":"5be5893250750f4e586fd637"},{"$oid":"5be5893250750f4e586fd630"},{"$oid":"5be5893250750f4e586fd63d"},{"$oid":"5be5893250750f4e586fd636"}],"username":"elena.prohaska5998","email":"elena.prohaska36@hotmail.com","tel":"069-915-2132","id":"5be5893250750f4e586fd62e","createdAt":{"$date":"2018-11-09T13:18:42.241Z"},"updatedAt":{"$date":"2018-11-09T13:29:35.789Z"},"salt":"JVhEukH2eZwF6Wj6pNJNYQ==","__v":1}
{"_id":{"$oid":"5be5893250750f4e586fd62f"},"active":true,"firstName":"Winifred","lastName":"Waters","photoUrl":"https://s3.amazonaws.com/uifaces/faces/twitter/justinrgraham/128.jpg","company":"Douglas, Batz and Nolan Corp.","position":"Purchasing manager","password":"4v6E+gvShqDIeeBX1ZijuNxChNTLYjgO2XnOJnpEUhE=","contacts":[{"$oid":"5be5893250750f4e586fd62d"},{"$oid":"5be5893250750f4e586fd633"},{"$oid":"5be5893250750f4e586fd62e"},{"$oid":"5be5893250750f4e586fd62c"},{"$oid":"5be5893250750f4e586fd63b"},{"$oid":"5be5893250750f4e586fd63c"},{"$oid":"5be5893250750f4e586fd63e"},{"$oid":"5be5893250750f4e586fd635"},{"$oid":"5be5893250750f4e586fd63a"},{"$oid":"5be5893250750f4e586fd632"}],"username":"winifred_waters50","email":"winifredwaters77@gmail.com","tel":"018-773-3922 x82396","id":"5be5893250750f4e586fd62f","createdAt":{"$date":"2018-11-09T13:18:42.245Z"},"updatedAt":{"$date":"2018-11-09T13:29:35.794Z"},"salt":"QtIex4EVVy6RB2HHqpec5Q==","__v":1}
{"_id":{"$oid":"5be5893250750f4e586fd630"},"active":true,"firstName":"Rodolfo","lastName":"Kerluke","photoUrl":"https://s3.amazonaws.com/uifaces/faces/twitter/andrea211087/128.jpg","company":"Wilderman, Schuppe and Wiegand Corp.","position":"Foreperson, supervisor, lead person","password":"EoGQryjhSfI+GAX+DYjZfnO8oojfMc6H+vVzysyGtb0=","contacts":[{"$oid":"5be5893250750f4e586fd62d"},{"$oid":"5be5893250750f4e586fd631"},{"$oid":"5be5893250750f4e586fd633"},{"$oid":"5be5893250750f4e586fd639"},{"$oid":"5be5893250750f4e586fd63a"},{"$oid":"5be5893250750f4e586fd634"},{"$oid":"5be5893250750f4e586fd62c"},{"$oid":"5be5893250750f4e586fd63d"},{"$oid":"5be5893250750f4e586fd636"},{"$oid":"5be5893250750f4e586fd632"},{"$oid":"5be5893250750f4e586fd635"},{"$oid":"5be5893250750f4e586fd62f"}],"username":"rodolfo.kerluke0651","email":"rodolfo73@yahoo.com","tel":"168.128.0217","id":"5be5893250750f4e586fd630","createdAt":{"$date":"2018-11-09T13:18:42.251Z"},"updatedAt":{"$date":"2018-11-09T13:29:35.800Z"},"salt":"R9Qpym+cVr+IhwKcFo/KYQ==","__v":1}
{"_id":{"$oid":"5be5893250750f4e586fd631"},"active":true,"firstName":"Meghan","lastName":"Adams","photoUrl":"https://s3.amazonaws.com/uifaces/faces/twitter/leemunroe/128.jpg","company":"Pacocha, Bauch and Hodkiewicz LLC","position":"Office manager.","password":"lHgyH4ExMoqRbIiHbtmobrmOHOJJCvLA0VPIYJlehMo=","contacts":[{"$oid":"5be5893250750f4e586fd62e"},{"$oid":"5be5893250750f4e586fd630"},{"$oid":"5be5893250750f4e586fd639"},{"$oid":"5be5893250750f4e586fd637"},{"$oid":"5be5893250750f4e586fd635"},{"$oid":"5be5893250750f4e586fd636"},{"$oid":"5be5893250750f4e586fd63d"},{"$oid":"5be5893250750f4e586fd62d"},{"$oid":"5be5893250750f4e586fd632"},{"$oid":"5be5893250750f4e586fd63b"}],"username":"meghan.adams54","email":"meghan.adams@gmail.com","tel":"010.706.0602","id":"5be5893250750f4e586fd631","createdAt":{"$date":"2018-11-09T13:18:42.257Z"},"updatedAt":{"$date":"2018-11-09T13:29:35.807Z"},"salt":"N1zFcsznekdT5iBhPHUI3w==","__v":1}
{"_id":{"$oid":"5be5893250750f4e586fd632"},"active":true,"firstName":"Joy","lastName":"Cormier","photoUrl":"https://s3.amazonaws.com/uifaces/faces/twitter/thaodang17/128.jpg","company":"Langosh, Deckow and Bednar Ltd.","position":"Office manager.","password":"nFYRkCmxgvZ0IW03RJcmIuK+nN2Jzcf4KycYmp5/x6E=","contacts":[{"$oid":"5be5893250750f4e586fd62c"},{"$oid":"5be5893250750f4e586fd634"},{"$oid":"5be5893250750f4e586fd633"},{"$oid":"5be5893250750f4e586fd631"},{"$oid":"5be5893250750f4e586fd639"},{"$oid":"5be5893250750f4e586fd62d"},{"$oid":"5be5893250750f4e586fd638"},{"$oid":"5be5893250750f4e586fd636"},{"$oid":"5be5893250750f4e586fd62f"},{"$oid":"5be5893250750f4e586fd62e"}],"username":"joy36","email":"joycormier18@yahoo.com","tel":"(363) 689-8930 x525","id":"5be5893250750f4e586fd632","createdAt":{"$date":"2018-11-09T13:18:42.262Z"},"updatedAt":{"$date":"2018-11-09T13:29:35.813Z"},"salt":"4YVmSt16G0kxo7bFYXfIWQ==","__v":1}
{"_id":{"$oid":"5be5893250750f4e586fd633"},"active":true,"firstName":"Laverne","lastName":"Sanford","photoUrl":"https://s3.amazonaws.com/uifaces/faces/twitter/lhausermann/128.jpg","company":"Williamson Group","position":"Receptionist","password":"kWu64yp4OltQb7icxdbMANoAEGgmMav7c7EslU0Iyd4=","contacts":[{"$oid":"5be5893250750f4e586fd634"},{"$oid":"5be5893250750f4e586fd637"},{"$oid":"5be5893250750f4e586fd635"},{"$oid":"5be5893250750f4e586fd632"},{"$oid":"5be5893250750f4e586fd631"}],"username":"laverne_sanford60","email":"laverne12@yahoo.com","tel":"1-093-380-8737 x24781","id":"5be5893250750f4e586fd633","createdAt":{"$date":"2018-11-09T13:18:42.271Z"},"updatedAt":{"$date":"2018-11-09T13:29:35.819Z"},"salt":"mBTaxUcyQQSlXptZNAXkEA==","__v":1}
{"_id":{"$oid":"5be5893250750f4e586fd634"},"active":true,"firstName":"Ruth","lastName":"Fisher","photoUrl":"https://s3.amazonaws.com/uifaces/faces/twitter/rahmeen/128.jpg","company":"Hane-Windler Group","position":"Receptionist","password":"MJay26MgZnDKUclfOOIwDoVn4k8DDJBGX+DMFYImY+w=","contacts":[{"$oid":"5be5893250750f4e586fd633"},{"$oid":"5be5893250750f4e586fd63e"},{"$oid":"5be5893250750f4e586fd62c"},{"$oid":"5be5893250750f4e586fd632"},{"$oid":"5be5893250750f4e586fd637"},{"$oid":"5be5893250750f4e586fd63b"},{"$oid":"5be5893250750f4e586fd639"},{"$oid":"5be5893250750f4e586fd63c"},{"$oid":"5be5893250750f4e586fd630"},{"$oid":"5be5893250750f4e586fd635"},{"$oid":"5be5893250750f4e586fd62f"}],"username":"ruthfisher64","email":"ruth.fisher48@hotmail.com","tel":"661.211.4654","id":"5be5893250750f4e586fd634","createdAt":{"$date":"2018-11-09T13:18:42.277Z"},"updatedAt":{"$date":"2018-11-09T13:29:35.825Z"},"salt":"dnnx/3Yr7g88gN/EeLWf+g==","__v":1}
{"_id":{"$oid":"5be5893250750f4e586fd635"},"active":true,"firstName":"Gilbert","lastName":"Stark","photoUrl":"https://s3.amazonaws.com/uifaces/faces/twitter/moynihan/128.jpg","company":"Jacobs, Brakus and McClure Ltd.","position":"Shipping and receiving person or manager","password":"H6m6rwX4P7tL5YNTmUlPCGfPXlKggfoMqN93wEuzLdw=","contacts":[{"$oid":"5be5893250750f4e586fd632"},{"$oid":"5be5893250750f4e586fd633"},{"$oid":"5be5893250750f4e586fd634"},{"$oid":"5be5893250750f4e586fd638"},{"$oid":"5be5893250750f4e586fd62e"},{"$oid":"5be5893250750f4e586fd639"}],"username":"gilbert_stark","email":"gilbertstark53@yahoo.com","tel":"(140) 587-1907","id":"5be5893250750f4e586fd635","createdAt":{"$date":"2018-11-09T13:18:42.282Z"},"updatedAt":{"$date":"2018-11-09T13:29:35.830Z"},"salt":"ArLA7yhPk2Q3yiimU6VE4g==","__v":1}
{"_id":{"$oid":"5be5893250750f4e586fd636"},"active":true,"firstName":"Cristina","lastName":"Blick","photoUrl":"https://s3.amazonaws.com/uifaces/faces/twitter/lepinski/128.jpg","company":"King LLC","position":"Accountant, bookkeeper, controller","password":"XdABbkMniJY+j/ofX4bO6BsfemVHEs5E+mgixIFL1VI=","contacts":[{"$oid":"5be5893250750f4e586fd62c"},{"$oid":"5be5893250750f4e586fd631"},{"$oid":"5be5893250750f4e586fd639"},{"$oid":"5be5893250750f4e586fd630"},{"$oid":"5be5893250750f4e586fd63a"},{"$oid":"5be5893250750f4e586fd62f"},{"$oid":"5be5893250750f4e586fd633"},{"$oid":"5be5893250750f4e586fd63d"}],"username":"cristina_blick07","email":"cristinablick42@yahoo.com","tel":"(406) 568-6685","id":"5be5893250750f4e586fd636","createdAt":{"$date":"2018-11-09T13:18:42.289Z"},"updatedAt":{"$date":"2018-11-09T13:29:35.838Z"},"salt":"EQMGUKJmIFxMBcyVsS7qyA==","__v":1}
{"_id":{"$oid":"5be5893250750f4e586fd637"},"active":true,"firstName":"Leslie","lastName":"Jast","photoUrl":"https://s3.amazonaws.com/uifaces/faces/twitter/jcubic/128.jpg","company":"Block-Medhurst Inc.","position":"Operations manager","password":"B0//6WrDn3FMUCB7lY0kStvCwg48Ngrsn7WP7nKEdP0=","contacts":[{"$oid":"5be5893250750f4e586fd638"},{"$oid":"5be5893250750f4e586fd632"},{"$oid":"5be5893250750f4e586fd634"},{"$oid":"5be5893250750f4e586fd630"},{"$oid":"5be5893250750f4e586fd62e"},{"$oid":"5be5893250750f4e586fd63d"},{"$oid":"5be5893150750f4e586fd62b"},{"$oid":"5be5893250750f4e586fd62c"},{"$oid":"5be5893250750f4e586fd62d"},{"$oid":"5be5893250750f4e586fd63c"},{"$oid":"5be5893250750f4e586fd62f"},{"$oid":"5be5893250750f4e586fd631"},{"$oid":"5be5893250750f4e586fd63a"}],"username":"leslie.jast76","email":"leslie.jast45@gmail.com","tel":"866.045.2540 x421","id":"5be5893250750f4e586fd637","createdAt":{"$date":"2018-11-09T13:18:42.295Z"},"updatedAt":{"$date":"2018-11-09T13:29:35.844Z"},"salt":"vWmKKeU0/UOtcbNyRhsGQA==","__v":1}
{"_id":{"$oid":"5be5893250750f4e586fd638"},"active":true,"firstName":"Andres","lastName":"Abernathy","photoUrl":"https://s3.amazonaws.com/uifaces/faces/twitter/sawrb/128.jpg","company":"Weber Inc.","position":"Operations manager","password":"0KBZW2/Pf1P3KRxSuVsadBTFX8ukzYihseQ3ClDZt64=","contacts":[{"$oid":"5be5893250750f4e586fd63b"},{"$oid":"5be5893250750f4e586fd636"},{"$oid":"5be5893250750f4e586fd62f"},{"$oid":"5be5893250750f4e586fd62c"},{"$oid":"5be5893250750f4e586fd63c"},{"$oid":"5be5893250750f4e586fd63a"},{"$oid":"5be5893250750f4e586fd63d"},{"$oid":"5be5893250750f4e586fd632"},{"$oid":"5be5893250750f4e586fd62e"},{"$oid":"5be5893250750f4e586fd639"},{"$oid":"5be5893250750f4e586fd630"},{"$oid":"5be5893250750f4e586fd62d"}],"username":"andres40","email":"andres.abernathy40@hotmail.com","tel":"(663) 759-8232","id":"5be5893250750f4e586fd638","createdAt":{"$date":"2018-11-09T13:18:42.303Z"},"updatedAt":{"$date":"2018-11-09T13:29:35.849Z"},"salt":"hfG3Ay/CDLYn8mq54Lz7gQ==","__v":1}
{"_id":{"$oid":"5be5893250750f4e586fd639"},"active":true,"firstName":"Wanda","lastName":"Jenkins","photoUrl":"https://s3.amazonaws.com/uifaces/faces/twitter/jay_wilburn/128.jpg","company":"Lang, Schiller and Jerde Ltd.","position":"Receptionist","password":"EDC57K3+XjmXa19lBlDiFdV2MyJCNVIS74bPK8Bz3ro=","contacts":[{"$oid":"5be5893250750f4e586fd62d"},{"$oid":"5be5893250750f4e586fd63a"},{"$oid":"5be5893150750f4e586fd62b"},{"$oid":"5be5893250750f4e586fd630"},{"$oid":"5be5893250750f4e586fd62e"},{"$oid":"5be5893250750f4e586fd63d"},{"$oid":"5be5893250750f4e586fd636"},{"$oid":"5be5893250750f4e586fd62c"},{"$oid":"5be5893250750f4e586fd638"}],"username":"wanda.jenkins77","email":"wanda.jenkins@yahoo.com","tel":"(122) 001-2161 x573","id":"5be5893250750f4e586fd639","createdAt":{"$date":"2018-11-09T13:18:42.311Z"},"updatedAt":{"$date":"2018-11-09T13:29:35.856Z"},"salt":"9dONjL8rigDm/D4MZS7NXA==","__v":1}
{"_id":{"$oid":"5be5893250750f4e586fd63a"},"active":true,"firstName":"Hope","lastName":"Kovacek","photoUrl":"https://s3.amazonaws.com/uifaces/faces/twitter/rmlewisuk/128.jpg","company":"Gleichner, Kiehn and Moen Group","position":"Purchasing manager","password":"vGD18l/iBDHQqiUAI/MJ7LenzVD4kAiAB796JjRbyRM=","contacts":[{"$oid":"5be5893250750f4e586fd635"},{"$oid":"5be5893250750f4e586fd62c"},{"$oid":"5be5893150750f4e586fd62b"},{"$oid":"5be5893250750f4e586fd632"}],"username":"hope.kovacek5874","email":"hope89@hotmail.com","tel":"(109) 489-7620 x5496","id":"5be5893250750f4e586fd63a","createdAt":{"$date":"2018-11-09T13:18:42.315Z"},"updatedAt":{"$date":"2018-11-09T13:29:35.861Z"},"salt":"XSPN7SLkEfioEyKnF/sB1w==","__v":1}
{"_id":{"$oid":"5be5893250750f4e586fd63b"},"active":true,"firstName":"Sammy","lastName":"Bailey","photoUrl":"https://s3.amazonaws.com/uifaces/faces/twitter/abovefunction/128.jpg","company":"Rosenbaum LLC","position":"Receptionist","password":"uEec9pU5PV6kfAPUI8WPsI75OfoKIZ8e9snDr9lUbZU=","contacts":[{"$oid":"5be5893250750f4e586fd636"},{"$oid":"5be5893250750f4e586fd635"},{"$oid":"5be5893250750f4e586fd62c"},{"$oid":"5be5893250750f4e586fd637"},{"$oid":"5be5893250750f4e586fd631"},{"$oid":"5be5893250750f4e586fd633"},{"$oid":"5be5893250750f4e586fd632"},{"$oid":"5be5893250750f4e586fd63a"},{"$oid":"5be5893250750f4e586fd630"},{"$oid":"5be5893250750f4e586fd638"},{"$oid":"5be5893250750f4e586fd63d"},{"$oid":"5be5893250750f4e586fd62e"},{"$oid":"5be5893250750f4e586fd639"}],"username":"sammybailey64","email":"sammy.bailey@gmail.com","tel":"446-208-4129 x483","id":"5be5893250750f4e586fd63b","createdAt":{"$date":"2018-11-09T13:18:42.320Z"},"updatedAt":{"$date":"2018-11-09T13:29:35.874Z"},"salt":"Q2LXAVFjUwyE2WoB15OO+A==","__v":1}
{"_id":{"$oid":"5be5893250750f4e586fd63c"},"active":true,"firstName":"Antoinette","lastName":"Stehr","photoUrl":"https://s3.amazonaws.com/uifaces/faces/twitter/ah_lice/128.jpg","company":"Bauch, Schaden and Batz Corp.","position":"Purchasing manager","password":"HSx2bXi6WlsEYlbkXtWMweLe5GBGCX/yO5LxI6PFEHc=","contacts":[{"$oid":"5be5893250750f4e586fd63b"},{"$oid":"5be5893250750f4e586fd638"}],"username":"antoinette.stehr87","email":"antoinette.stehr@hotmail.com","tel":"1-121-865-2453","id":"5be5893250750f4e586fd63c","createdAt":{"$date":"2018-11-09T13:18:42.326Z"},"updatedAt":{"$date":"2018-11-09T13:29:35.879Z"},"salt":"UN/d3N17s3LGDygA0ohA0g==","__v":1}
{"_id":{"$oid":"5be5893250750f4e586fd63d"},"active":true,"firstName":"Jerald","lastName":"Sanford","photoUrl":"https://s3.amazonaws.com/uifaces/faces/twitter/kianoshp/128.jpg","company":"Runte, Wisoky and Konopelski LLC","position":"Receptionist","password":"214wtjW0eGm1sF3FbFUjsEXx6P9+ab4F5qaYkLhXb28=","contacts":[{"$oid":"5be5893250750f4e586fd630"},{"$oid":"5be5893250750f4e586fd63b"},{"$oid":"5be5893250750f4e586fd638"},{"$oid":"5be5893250750f4e586fd635"},{"$oid":"5be5893250750f4e586fd633"}],"username":"jerald.sanford9397","email":"jeraldsanford48@hotmail.com","tel":"956-553-7632 x714","id":"5be5893250750f4e586fd63d","createdAt":{"$date":"2018-11-09T13:18:42.330Z"},"updatedAt":{"$date":"2018-11-09T13:29:35.886Z"},"salt":"nhY1wqxONht7aoN5W1wagQ==","__v":1}
{"_id":{"$oid":"5be5893250750f4e586fd63e"},"active":true,"firstName":"Shane","lastName":"Marks","photoUrl":"https://s3.amazonaws.com/uifaces/faces/twitter/exentrich/128.jpg","company":"Stark-Schinner LLC","position":"Professional staff","password":"SZGx+PCmwSJUPFFM2+ZKw4Gf+J6hGTKXGJdifEtLZQk=","contacts":[{"$oid":"5be5893250750f4e586fd635"},{"$oid":"5be5893250750f4e586fd63d"},{"$oid":"5be5893250750f4e586fd632"}],"username":"shane49","email":"shane.marks@hotmail.com","tel":"1-530-925-8561 x438","id":"5be5893250750f4e586fd63e","createdAt":{"$date":"2018-11-09T13:18:42.338Z"},"updatedAt":{"$date":"2018-11-09T13:29:35.891Z"},"salt":"y5C2N6pOEYT7fiIAPHhbVg==","__v":1}
